{
  "type": "minecraft:archaeology",
  "pools": [
    {
      "bonus_rolls": 0.0,
      "entries": [
        {
          "type": "minecraft:item",
          "name": "minecraft:archer_pottery_sherd"
        },
        {
          "type": "minecraft:item",
          "name": "minecraft:miner_pottery_sherd"
        },
        {
          "type": "minecraft:item",
          "name": "minecraft:prize_pottery_sherd"
        },
        {
          "type": "minecraft:item",
          "name": "minecraft:skull_pottery_sherd"
        },
        {
          "type": "minecraft:item",
          "name": "minecraft:diamond"
        },
        {
          "type": "minecraft:item",
          "name": "minecraft:tnt"
        },
        {
          "type": "minecraft:item",
          "name": "minecraft:gunpowder"
        },
        {
          "type": "minecraft:item",
          "name": "minecraft:emerald"
        },
        {
          "type": "minecraft:loot_table",
          "name": "cam:misc/weapon_debris",
          "conditions": [
              {
                  "condition": "minecraft:value_check",
                  "value": {
                      "type": "score",
                      "target": {
                          "type": "fixed",
                          "name": "#others"
                      },
                      "score": "CAM_module"
                  },
                  "range": 1
              }
          ]
      }
      ],
      "rolls": 1.0
    }
  ],
  "random_sequence": "minecraft:archaeology/desert_pyramid"
}